__init__.py
csv_helper.py
logger_helper.py
path_helper.py
time_helper.py
helpers_alphonseluca-0.0.1.dist-info/LICENSE
helpers_alphonseluca-0.0.1.dist-info/METADATA
helpers_alphonseluca-0.0.1.dist-info/WHEEL
helpers_alphonseluca-0.0.1.dist-info/top_level.txt
helpers_alphonseluca-0.0.1.dist-info/RECORD
